{
"type": "FeatureCollection",
"name": "xa_sample-6-gps",
"crs": { "type": "name", "properties": { "name": "urn:ogc:def:crs:OGC:1.3:CRS84" } },
"features": [
{ "type": "Feature", "properties": { "seq": 0, "sub_seq": 0, "loc_type": "s" }, "geometry": { "type": "Point", "coordinates": [ 104.08419, 30.65651 ] } },
{ "type": "Feature", "properties": { "seq": 1, "sub_seq": 0, "loc_type": "s" }, "geometry": { "type": "Point", "coordinates": [ 104.08432, 30.65728 ] } },
{ "type": "Feature", "properties": { "seq": 2, "sub_seq": 0, "loc_type": "s" }, "geometry": { "type": "Point", "coordinates": [ 104.084, 30.65625 ] } },
{ "type": "Feature", "properties": { "seq": 3, "sub_seq": 0, "loc_type": "s" }, "geometry": { "type": "Point", "coordinates": [ 104.08392, 30.65613 ] } },
{ "type": "Feature", "properties": { "seq": 4, "sub_seq": 0, "loc_type": "s" }, "geometry": { "type": "Point", "coordinates": [ 104.08386, 30.65605 ] } },
{ "type": "Feature", "properties": { "seq": 5, "sub_seq": 0, "loc_type": "s" }, "geometry": { "type": "Point", "coordinates": [ 104.08396, 30.65598 ] } },
{ "type": "Feature", "properties": { "seq": 6, "sub_seq": 0, "loc_type": "s" }, "geometry": { "type": "Point", "coordinates": [ 104.08396, 30.65598 ] } },
{ "type": "Feature", "properties": { "seq": 7, "sub_seq": 0, "loc_type": "s" }, "geometry": { "type": "Point", "coordinates": [ 104.08372, 30.65586 ] } },
{ "type": "Feature", "properties": { "seq": 8, "sub_seq": 0, "loc_type": "s" }, "geometry": { "type": "Point", "coordinates": [ 104.08262, 30.65447 ] } },
{ "type": "Feature", "properties": { "seq": 9, "sub_seq": 0, "loc_type": "s" }, "geometry": { "type": "Point", "coordinates": [ 104.0821, 30.65382 ] } }
]
}
